ytdlp_simple_api/__init__.py
ytdlp_simple_api/__main__.py
ytdlp_simple_api/api.py
ytdlp_simple_api/config.py
ytdlp_simple_api/depend.py
ytdlp_simple_api/models.py
ytdlp_simple_api/utils.py
ytdlp_simple_api/static/cookies.css
ytdlp_simple_api/static/cookies.html
ytdlp_simple_api/static/cookies.js
ytdlp_simple_api/static/ui.css
ytdlp_simple_api/static/ui.html
ytdlp_simple_api/static/ui.js
ytdlp_simple_api-0.0.5.dist-info/METADATA
ytdlp_simple_api-0.0.5.dist-info/WHEEL
ytdlp_simple_api-0.0.5.dist-info/licenses/LICENSE
ytdlp_simple_api-0.0.5.dist-info/RECORD
