Metadata-Version: 2.4
Name: ytdlp-simple-api
Version: 0.0.5
Summary: API for downloading media from YouTube and other platforms with various download modes, and manages cookies for accessing content that requires authorization.
Project-URL: Homepage, https://github.com/imbecility/ytdlp-simple-api
License-Expression: MIT
License-File: LICENSE
Classifier: Operating System :: Microsoft :: Windows
Classifier: Operating System :: POSIX :: Linux
Classifier: Programming Language :: Python :: 3
Classifier: Topic :: Multimedia
Requires-Python: >=3.10
Requires-Dist: fastapi>=0.128.0
Requires-Dist: python-multipart>=0.0.22
Requires-Dist: uvicorn>=0.40.0
Requires-Dist: ytdlp-simple
